ipyLogger
